k_load/__init__.py
k_load/__main__.py
k_load/common.py
k_load/downloaders.py
k_load/extractors.py
k_load-0.2.8.dist-info/METADATA
k_load-0.2.8.dist-info/RECORD
k_load-0.2.8.dist-info/WHEEL
k_load-0.2.8.dist-info/entry_points.txt
k_load-0.2.8.dist-info/top_level.txt
