Metadata-Version: 2.1
Name: k-load
Version: 0.2.8
Summary: A downloader
Home-page: https://github.com/T-K-233/k-load
Author: -T.K.-
Author-email: tk.fantasy.233@gmail.com
License: UNKNOWN
Platform: UNKNOWN
Classifier: Programming Language :: Python :: 3
Classifier: License :: OSI Approved :: MIT License
Classifier: Operating System :: OS Independent
